AUTHORS.rst
CONTRIBUTING.rst
HISTORY.rst
LICENSE
MANIFEST.in
README.rst
setup.cfg
setup.py
sales_menu/__init__.py
sales_menu/admin.py
sales_menu/models.py
sales_menu.egg-info/PKG-INFO
sales_menu.egg-info/SOURCES.txt
sales_menu.egg-info/dependency_links.txt
sales_menu.egg-info/not-zip-safe
sales_menu.egg-info/top_level.txt
sales_menu/templatetags/__init__.py
sales_menu/templatetags/menu_tags.py