Metadata-Version: 1.1
Name: sales-menu
Version: 0.1.1
Summary: The simple menu for Django.
Home-page: https://github.com/s-m-i-t-a/sales_menu
Author: Jindřich Smitka
Author-email: smitka.j@gmail.com
License: BSD
Keywords: sales_menu
Platform: UNKNOWN
Classifier: Development Status :: 2 - Pre-Alpha
Classifier: Framework :: Django
Classifier: Intended Audience :: Developers
Classifier: License :: OSI Approved :: BSD License
Classifier: Natural Language :: English
Classifier: Programming Language :: Python :: 2
Classifier: Programming Language :: Python :: 2.6
Classifier: Programming Language :: Python :: 2.7
Classifier: Programming Language :: Python :: 3
Classifier: Programming Language :: Python :: 3.3
